skflex/__init__.py
skflex/skflex.py
skflex-1.0.2.dist-info/METADATA
skflex-1.0.2.dist-info/WHEEL
skflex-1.0.2.dist-info/top_level.txt
skflex-1.0.2.dist-info/RECORD
