Metadata-Version: 2.1
Name: skflex
Version: 1.0.2
Summary: skflex provides a suite of flexible utility functions for use with the sklearn library
Home-page: https://github.com/LTW85/skflex
Author: Liam Wright
Author-email: ltw85.develop@gmail.com
License: UNKNOWN
Platform: UNKNOWN
Classifier: Programming Language :: Python :: 3
Classifier: License :: OSI Approved :: MIT License
Classifier: Operating System :: OS Independent
Classifier: Development Status :: 5 - Production/Stable
Classifier: Topic :: Utilities
